hankify_pw/__init__.py
hankify_pw/hankify_pw.py
hankify_pw/words.txt
hankify_pw-1.1.0.dist-info/LICENSE
hankify_pw-1.1.0.dist-info/METADATA
hankify_pw-1.1.0.dist-info/WHEEL
hankify_pw-1.1.0.dist-info/entry_points.txt
hankify_pw-1.1.0.dist-info/top_level.txt
hankify_pw-1.1.0.dist-info/RECORD
