Metadata-Version: 2.1
Name: hankify-pw
Version: 1.1.0
Summary: Generate Hank Preston-y passwords
Home-page: https://github.com/xorrkaz/hankify-pw
Author: Joe Clarke
Author-email: jclarke@cisco.com
License: MIT
Keywords: Elemental
Platform: UNKNOWN
Classifier: Intended Audience :: Developers
Classifier: License :: OSI Approved :: MIT License
Classifier: Programming Language :: Python :: 3.6
Requires-Python: >=3.6
